Metadata-Version: 1.0
Name: django-minimal-abstract-user
Version: 0.0.2
Summary: UNKNOWN
Home-page: https://github.com/IlyaSemenov/django-minimal-abstract-user
Author: Ilya Semenov
Author-email: ilya@semenov.co
License: BSD
Platform: UNKNOWN
